nqntnqnqmb/__init__.py
nqntnqnqmb/core.py
nqntnqnqmb-1.1.dist-info/METADATA
nqntnqnqmb-1.1.dist-info/WHEEL
nqntnqnqmb-1.1.dist-info/top_level.txt
nqntnqnqmb-1.1.dist-info/RECORD
