Metadata-Version: 2.1
Name: nqntnqnqmb
Version: 1.1
Summary: nqntnqnqmb.
Home-page: http://github.com/megadose/nqntnqnqmb
Author: megadose
Author-email: UNKNOWN
License: UNKNOWN
Platform: UNKNOWN
Classifier: Programming Language :: Python
Classifier: License :: OSI Approved :: GNU General Public License v3 (GPLv3)
Requires-Dist: requests
Requires-Dist: fake-useragent
Requires-Dist: bs4
Requires-Dist: argparse
